tmx2txt/__init__.py
tmx2txt/__main__.py
tmx2txt/tmx2txt.py
tmx2txt-1.0.0.dist-info/LICENSE.txt
tmx2txt-1.0.0.dist-info/METADATA
tmx2txt-1.0.0.dist-info/WHEEL
tmx2txt-1.0.0.dist-info/entry_points.txt
tmx2txt-1.0.0.dist-info/top_level.txt
tmx2txt-1.0.0.dist-info/RECORD
